{"url": "https://www.baaa-acro.com/crash/crash-consolidated-pb4y-2-privateer-whidbey-island-nas-5-killed", "date": "Jul 22, 1947", "type": "Consolidated PB4Y-2 Privateer", "operator": "US%20Navy", "flight_phase": "Landing (descent or approach)", "flight_type": "Survey / Patrol / Reconnaissance", "survivors": "No", "site": "Airport (less than 10 km from airport)", "schedule": "Whidbey Island - Whidbey Island", "msn": "59821", "yom": 1943, "flight_number": null, "city": "Whidbey Island NAS (Ault Field)", "zone": "Washington", "country": "United States of America", "region": "North America", "crew_on_board": 5, "crew_fatalities": 5, "pax_on_board": 0, "pax_fatalities": 0, "other_fatalities": 0, "total_fatalities": 5, "captain_hours": null, "captain_hours_type": null, "copilot_hours": null, "copilot_hours_type": null, "aircraft_hours": null, "circumstances": "On final approach to Whidbey Island-Ault Field NAS, the aircraft was too low, hit tree tops and crashed in flames. All five crew members were killed. ", "probable_cause": null}