{"url": "https://www.baaa-acro.com/crash/crash-de-havilland-dhc-2-beaver-sedro-woolley", "date": "Jun 8, 1987 at 1203 LT", "type": "De Havilland DHC-2 Beaver", "operator": "James B. Hayton", "flight_phase": "Takeoff (climb)", "flight_type": "Private", "survivors": "Yes", "site": "Plain, Valley", "schedule": "Sedro-Woolley - Renton", "msn": "622", "yom": 1954, "flight_number": null, "city": "Sedro-Woolley", "zone": "Washington", "country": "United States of America", "region": "North America", "crew_on_board": 1, "crew_fatalities": 0, "pax_on_board": 0, "pax_fatalities": 0, "other_fatalities": 0, "total_fatalities": 0, "captain_hours": 24000, "captain_hours_type": 127, "copilot_hours": null, "copilot_hours_type": null, "aircraft_hours": 16008, "circumstances": "Shortly after takeoff a loss of power occurred and the aircraft struck trees in flight. Less than 1/2 fuel was available in all three fuel tanks. The fuel selector valve was tested and found that the selections plate was indexed off center for all selections due to wear. In the takeoff attitude unporting occurred allowing air to be drawn into the system. The pilot escaped with minor injuries. ", "probable_cause": "Occurrence #1: loss of engine power (partial) - mech failure/malf\r\nPhase of operation: takeoff - initial climb\r\nFindings\r\n1. (c) fuel system, selector/valve - worn\r\n2. (c) fluid, fuel - starvation\r\n----------\r\nOccurrence #2: forced landing\r\nPhase of operation: descent - emergency\r\n----------\r\nOccurrence #3: in flight collision with terrain/water\r\nPhase of operation: descent\r\nFindings\r\n3. (f) terrain condition - high obstruction(s)\r\n4. (c) clearance - not possible"}