{"url": "https://www.baaa-acro.com/crash/crash-vickers-416-wellington-ic-brest-6-killed-0", "date": "Jul 2, 1941", "type": "Vickers 416 Wellington IC", "operator": "Royal-Air-Force-4", "flight_phase": "Flight", "flight_type": "Bombing", "survivors": "No", "site": "Lake, Sea, Ocean, River", "schedule": "Mildenhall - Mildenhall", "msn": null, "yom": null, "flight_number": null, "city": "Brest", "zone": "Finist\u00e8re", "country": "France", "region": "Europe", "crew_on_board": 6, "crew_fatalities": 6, "pax_on_board": 0, "pax_fatalities": 0, "other_fatalities": 0, "total_fatalities": 6, "captain_hours": null, "captain_hours_type": null, "copilot_hours": null, "copilot_hours_type": null, "aircraft_hours": null, "circumstances": "The airplane departed RAF Mildenhall at 2238LT on July 1st on an operation to Brest. While approaching the target area, it was shot down by enemy fire and crashed into the sea. All six crew members were killed. \r\nCrew:\r\nSgt William Mervyn Symmons, pilot, \r\nP/O Standish Locksley St. Vincent-Welch, pilot,\r\nSgt William James Megran, observer, \r\nSgt Cecil Charles Reidmuller, wireless operator, \r\nSgt Robert Harland Crafts, wireless operator, \r\nF/Sgt Anthony Robert James Harrison, air gunner.", "probable_cause": "Shot down by enemy fire. "}