{"url": "https://www.baaa-acro.com/crash/crash-pzl-mielec-2v-near-khantaiskoye-ozero-1-killed", "date": "Dec 24, 1973 at 1926 LT", "type": "PZL-Mielec AN-2", "operator": "Aeroflot-3", "flight_phase": "Flight", "flight_type": "Cargo", "survivors": "Yes", "site": "Mountains", "schedule": "Dudinka \u2013 Khantaiskoye Ozero", "msn": "1G102-09", "yom": 1969, "flight_number": null, "city": "Khantaiskoye Ozero", "zone": "Krasnoyarsk Krai", "country": "Russia", "region": "Asia", "crew_on_board": 2, "crew_fatalities": 1, "pax_on_board": 0, "pax_fatalities": 0, "other_fatalities": 0, "total_fatalities": 1, "captain_hours": null, "captain_hours_type": null, "copilot_hours": null, "copilot_hours_type": null, "aircraft_hours": 4840, "circumstances": "On a cargo flight from Dudinka to Khantaiskoye Ozero settlement (Taimyr) during the polar night when the crew decided to cut the route short although visibility was poor. On approach to Khantaiskoye Ozero, crew was unable to establish the position of the aircraft as the frequency of the radio beacon at Khantaiskoye Ozero had been changed without notice. The crew started the descent when the aircraft crashed at a height of 1,016 metres into the northern slope of a mountain (1,044 metres high) located some 28 km east of Khantaiskoye Ozero. The copilot was killed and the captain was seriously injured and rescued two days later, on December 26, 1973.", "probable_cause": "Wrong decisions taken en route by the crew who decided to modify his itinerary. The frequency of the radio beacon at destination had been changed without notice, which was considered as a contributory factor. "}