{"url": "https://www.baaa-acro.com/crash/crash-avro-652-anson-i-simonsbath-5-killed", "date": "Nov 28, 1939", "type": "Avro 652 Anson", "operator": "Royal-Air-Force-4", "flight_phase": "Flight", "flight_type": "Training", "survivors": "No", "site": "Mountains", "schedule": "Harwell - Harwell", "msn": null, "yom": null, "flight_number": null, "city": "Simonsbath", "zone": "Somerset", "country": "United Kingdom", "region": "Europe", "crew_on_board": 5, "crew_fatalities": 5, "pax_on_board": 0, "pax_fatalities": 0, "other_fatalities": 0, "total_fatalities": 5, "captain_hours": null, "captain_hours_type": null, "copilot_hours": null, "copilot_hours_type": null, "aircraft_hours": null, "circumstances": "The crew was performing a night cross-country flight out from RAF Harwell. En route, the twin engine aircraft crashed on hilly terrain in Simonsbath. The wreckage was found 40 hours later in the Exmoor National Park. All five crewmen were killed.\r\nCrew (148th Squadron):\r\nF/O Thomas William Storey, pilot,\r\nSgt Thomas Robert Moss, observer,\r\nSgt Gerald Roland Cecil Talbot, observer, \r\nAC1 Arthur John Whittaker, wireless operator and gunner, \r\nAC2 Frederick Challenger Overall.", "probable_cause": null}