{"url": "https://www.baaa-acro.com/crash/crash-douglas-dc-2a-127-salt-lake-city-3-killed", "date": "Oct 6, 1935", "type": "Douglas DC-2", "operator": "Standard-Oil-of-California.gif", "flight_phase": "Takeoff (climb)", "flight_type": "Ferry", "survivors": "No", "site": "Lake, Sea, Ocean, River", "schedule": null, "msn": "1328", "yom": 1934, "flight_number": null, "city": "Salt Lake City", "zone": "Utah", "country": "United States of America", "region": "North America", "crew_on_board": 3, "crew_fatalities": 3, "pax_on_board": 0, "pax_fatalities": 0, "other_fatalities": 0, "total_fatalities": 3, "captain_hours": null, "captain_hours_type": null, "copilot_hours": null, "copilot_hours_type": null, "aircraft_hours": null, "circumstances": "The crew was flying back to his base in California. Shortly after takeoff from Salt Lake City Airport, while climbing, the aircraft went out of control and plunged into the Great Salt Lake. The aircraft sank quickly but all three occupants were able to evacuate the cabin. Unfortunately, they drowned while trying to reach the shore. The aircraft was owned by the Standard Oil of California, not the Standard Oil Company, defunct in 1914. ", "probable_cause": null}