{"url": "https://www.baaa-acro.com/crash/crash-pitcairn-pa-6-mailwing-huron-1-killed", "date": "Jul 22, 1930", "type": "Pitcairn PA-6 Mailwing", "operator": "Thompson%20Aeronautical%20Corpo", "flight_phase": "Flight", "flight_type": "Postal (mail)", "survivors": "No", "site": "Plain, Valley", "schedule": null, "msn": "28", "yom": 1929, "flight_number": null, "city": "Huron", "zone": "Ohio", "country": "United States of America", "region": "North America", "crew_on_board": 1, "crew_fatalities": 1, "pax_on_board": 0, "pax_fatalities": 0, "other_fatalities": 0, "total_fatalities": 1, "captain_hours": null, "captain_hours_type": null, "copilot_hours": null, "copilot_hours_type": null, "aircraft_hours": null, "circumstances": "The airplane crashed in foggy conditions, killing the pilot, sole on board.", "probable_cause": null}