{"url": "https://www.baaa-acro.com/crash/crash-curtiss-c-46d-15-cu-commando-near-merida-4-killed", "date": "Jan 21, 1959 at 1530 LT", "type": "Curtiss C-46 Commando", "operator": "LEBCA", "flight_phase": "Flight", "flight_type": "Charter/Taxi (Non Scheduled Revenue Flight)", "survivors": "No", "site": "Mountains", "schedule": "M\u00e9rida \u2013 Lagunillas \u2013 Maracaibo", "msn": "33411", "yom": 1945, "flight_number": null, "city": "M\u00e9rida", "zone": "M\u00e9rida", "country": "Venezuela", "region": "South America", "crew_on_board": 2, "crew_fatalities": 2, "pax_on_board": 2, "pax_fatalities": 2, "other_fatalities": 0, "total_fatalities": 4, "captain_hours": null, "captain_hours_type": null, "copilot_hours": null, "copilot_hours_type": null, "aircraft_hours": null, "circumstances": "The aircraft departed M\u00e9rida-Alberto Carnevalli Airport at 1505LT on a charter flight to Maracaibo with an intermediate stop at Lagunillas. After takeoff, while approaching El Callejon Pass at an altitude of 7,000 feet, the crew realized it would not be possible to clear the pass and decided to modify his route. Vertical to Ejido, the captain made a 180 turn, modified his heading to 030\u00b0 and continued to the northeast. Few minutes later, while cruising in clouds at an altitude of 13,500 feet, the airplane struck the slope of La Culata Peak and was destroyed upon impact. The wreckage was found few hours later and all four occupants have been killed. ", "probable_cause": "The accident was due to flying the aircraft at insufficient altitude over an area apparently unfamiliar to the pilot."}