{"url": "https://www.baaa-acro.com/crash/crash-avro-679-manchester-warmenhuizen-5-killed", "date": "Mar 26, 1942 at 0032 LT", "type": "Avro 679 Manchester", "operator": "Royal-Air-Force-4", "flight_phase": "Flight", "flight_type": "Bombing", "survivors": "Yes", "site": "Plain, Valley", "schedule": "Woolfox Lodge - Woolfox Lodge", "msn": null, "yom": null, "flight_number": null, "city": "Alkmaar", "zone": "North Holland", "country": "Netherlands", "region": "Europe", "crew_on_board": 7, "crew_fatalities": 5, "pax_on_board": 0, "pax_fatalities": 0, "other_fatalities": 0, "total_fatalities": 5, "captain_hours": null, "captain_hours_type": null, "copilot_hours": null, "copilot_hours_type": null, "aircraft_hours": null, "circumstances": "The aircraft left RAF Woolfox Lodge at 2045LT on March 25 on a bombing mission to Essen, Germany. While overflying The Netherlands, the aircraft was shot down by the pilot of a German fighter and crashed in flames in Warmenhuizen, some 10 km northwest of Alkmaar. Five crew members were killed while two other occupants were injured.\r\nCrew (61st Squadron):\r\nP/O John Ralph Hubbard, pilot, \u2020\r\nP/O Alastair William Buchan, pilot, \u2020\r\nP/O Robert Heggie, observer, \u2020\r\nSgt John George Clelland, wireless operator and air gunner, \u2020\r\nSgt Albert Wallace Baker, wireless operator and air gunner, \u2020\r\nSgt P. Jones, \r\nSgt T.C. Stanley.", "probable_cause": "Shot down by a German fighter."}