{"url": "https://www.baaa-acro.com/crash/crash-boeing-b-52g-105-bw-stratofortress-castle-afb", "date": "Feb 11, 1988", "type": "Boeing B-52 Stratofortress", "operator": "United%20States%20Air%20Force", "flight_phase": "Takeoff (climb)", "flight_type": "Military", "survivors": "Yes", "site": "Airport (less than 10 km from airport)", "schedule": "Castle - Castle", "msn": "464287", "yom": 1958, "flight_number": null, "city": "Castle AFB", "zone": "California", "country": "United States of America", "region": "North America", "crew_on_board": 0, "crew_fatalities": 0, "pax_on_board": 0, "pax_fatalities": 0, "other_fatalities": 0, "total_fatalities": 0, "captain_hours": null, "captain_hours_type": null, "copilot_hours": null, "copilot_hours_type": null, "aircraft_hours": null, "circumstances": "The crew was engaged in a training flight out of Castle AFB. During the takeoff roll, the decision to abort was taken for unknown reasons. Unable to stop within the remaining distance, the aircraft overran and came to rest. All crew members escaped uninjured while the aircraft was damaged beyond repair. ", "probable_cause": null}