{"url": "https://www.baaa-acro.com/crash/crash-beechcraft-3nmt-expeditor-bastia", "date": "Sep 14, 2021 at 1025 LT", "type": "Beechcraft D18", "operator": "Aerial Advantage", "flight_phase": "Takeoff (climb)", "flight_type": "Private", "survivors": "Yes", "site": "Airport (less than 10 km from airport)", "schedule": null, "msn": "A-764", "yom": 1952, "flight_number": null, "city": "Bastia-Poretta", "zone": "Haute-Corse", "country": "France", "region": "Europe", "crew_on_board": 1, "crew_fatalities": 0, "pax_on_board": 2, "pax_fatalities": 0, "other_fatalities": 0, "total_fatalities": 0, "captain_hours": null, "captain_hours_type": null, "copilot_hours": null, "copilot_hours_type": null, "aircraft_hours": null, "circumstances": "Shortly after takeoff from Bastia-Poretta Airport Runway 16, while in initial climb, the pilot encountered an unexpected situation and apparently attempted an emergency landing when the twin engine aircraft crashed in a plantation located 1,5 km south of the airport. The airplane slid for few dozen metres before coming to rest, bursting into flames. All three occupants were rescued, one was uninjured while both others were seriously injured due to burns. The aircraft was destroyed by a post crash fire. ", "probable_cause": null}