{"url": "https://www.baaa-acro.com/crash/crash-douglas-dc-6b-near-mendoza-3-killed", "date": "Oct 19, 1971", "type": "Douglas DC-6", "operator": "LADECO", "flight_phase": "Flight", "flight_type": "Cargo", "survivors": "No", "site": "Mountains", "schedule": "Mendoza - Santiago de Chile", "msn": "43270/187", "yom": 1951, "flight_number": null, "city": "Mendoza", "zone": "Mendoza", "country": "Argentina", "region": "South America", "crew_on_board": 3, "crew_fatalities": 3, "pax_on_board": 0, "pax_fatalities": 0, "other_fatalities": 0, "total_fatalities": 3, "captain_hours": null, "captain_hours_type": null, "copilot_hours": null, "copilot_hours_type": null, "aircraft_hours": null, "circumstances": "Few minutes after takeoff from Mendoza-El Plumerillo Airport, the crew reported technical problems and was cleared to return with the engine number one shut down. Shortly later, the airplane crashed on Mt Santa Elena located few km from the airport. All three crew members were killed. The aircraft was chartered to Aero Dominicana. ", "probable_cause": null}