{"url": "https://www.baaa-acro.com/crash/crash-lockheed-pv-1-ventura-ii-west-stow-2-killed", "date": "Jan 20, 1943", "type": "Lockheed PV-1 Ventura", "operator": "Royal-Air-Force-4", "flight_phase": "Flight", "flight_type": "Training", "survivors": "Yes", "site": "Plain, Valley", "schedule": "Feltwell - Feltwell", "msn": null, "yom": null, "flight_number": null, "city": "West Stow", "zone": "Suffolk", "country": "United Kingdom", "region": "Europe", "crew_on_board": 3, "crew_fatalities": 2, "pax_on_board": 0, "pax_fatalities": 0, "other_fatalities": 0, "total_fatalities": 2, "captain_hours": null, "captain_hours_type": null, "copilot_hours": null, "copilot_hours_type": null, "aircraft_hours": null, "circumstances": "While performing a training sortie from RAF Feltwell, the twin engine aircraft hit tree tops, crashed and disintegrated in a field near West Stow. Two crew members were killed while the navigator was seriously injured. For unknown reason, the pilot was flying at an insufficient altitude and did not detect the trees. \nCrew (487th Squadron):\nSgt Gerald John Abrey, pilot, \u2020\nSgt H. Aldridge, navigator, \nF/O Frederick Douglas Drake, wireless operator and air gunner. \u2020", "probable_cause": null}