{"url": "https://www.baaa-acro.com/crash/crash-vickers-408-wellington-ia-verdun-2-killed", "date": "Jun 15, 1940", "type": "Vickers 408 Wellington IA", "operator": "Royal-Air-Force-4", "flight_phase": "Flight", "flight_type": "Bombing", "survivors": "Yes", "site": "Plain, Valley", "schedule": "Marham - Marham", "msn": null, "yom": null, "flight_number": null, "city": "Verdun", "zone": "Meuse", "country": "France", "region": "Europe", "crew_on_board": 6, "crew_fatalities": 2, "pax_on_board": 0, "pax_fatalities": 0, "other_fatalities": 0, "total_fatalities": 2, "captain_hours": null, "captain_hours_type": null, "copilot_hours": null, "copilot_hours_type": null, "aircraft_hours": null, "circumstances": "The airplane departed RAF Marham at 2224LT on June 14 on a bombing mission over Leverkusen. In the early hours of June 15, it crashed in unknown circumstances near Verdun, possibly after being shot down by enemy fire. Two crew members were killed and four others became PoW.\r\nCrew:\r\nSgt Lionel Austin Morris, \u2020\r\nSgt W. Stevens,\r\nSgt N. Packer,\r\nSgt J. D. Foulser,\r\nSgt Reginald James Baghurst, \u2020\r\nP/O J. E. A. Foster.", "probable_cause": null}