{"url": "https://www.baaa-acro.com/crash/crash-antonov-2m-staroye-zhookovo-1-killed", "date": "May 6, 1984", "type": "Antonov AN-2", "operator": "Aeroflot-3", "flight_phase": "Flight", "flight_type": "Spraying (Agricultural)", "survivors": "No", "site": "Plain, Valley", "schedule": null, "msn": "6 006 01", "yom": 1967, "flight_number": null, "city": "Staroye Zhookovo", "zone": "Tula oblast", "country": "Russia", "region": "Asia", "crew_on_board": 1, "crew_fatalities": 1, "pax_on_board": 0, "pax_fatalities": 0, "other_fatalities": 0, "total_fatalities": 1, "captain_hours": null, "captain_hours_type": null, "copilot_hours": null, "copilot_hours_type": null, "aircraft_hours": 3843, "circumstances": "Sole on board, the pilot was completing a local spraying flight near the village of Staroye Zhookovo. While flying at low height, the aircraft entered a nose-up attitude then lost height and crashed in a wooded area, bursting into flames. The pilot was killed. ", "probable_cause": "It was determined that the trim tab went jammed in the full up position during flight. The exact cause could not be determined as the aircraft was totally destroyed by fire but it is believed that it was the consequence of the failure of the elevator trim control system. "}