{"url": "https://www.baaa-acro.com/crash/crash-curtiss-c-46a-60-ck-commando-china-4-killed", "date": "Apr 7, 1945", "type": "Curtiss C-46 Commando", "operator": "USAAF", "flight_phase": "Flight", "flight_type": "Military", "survivors": "No", "site": null, "schedule": "Hanchung \u2013 Liangshan", "msn": "282", "yom": 1944, "flight_number": null, "city": "China", "zone": "All China", "country": "China", "region": "Asia", "crew_on_board": 3, "crew_fatalities": 3, "pax_on_board": 1, "pax_fatalities": 1, "other_fatalities": 0, "total_fatalities": 4, "captain_hours": null, "captain_hours_type": null, "copilot_hours": null, "copilot_hours_type": null, "aircraft_hours": null, "circumstances": "Went out of control and crashed in unknown circumstances in an isolated area somewhere in China. The wreckage was never found.\r\nCrew:\r\nT/Sgt Francis P. Bufkin Jr.,\r\nF/O Robert M. Fiske,\r\nT/Sgt Bert N. Wright.", "probable_cause": null}