{"url": "https://www.baaa-acro.com/crash/crash-vickers-406-wellington-ii-barton-bendish", "date": "Sep 8, 1941 at 0430 LT", "type": "Vickers 406 Wellington II", "operator": "Royal-Air-Force-4", "flight_phase": "Flight", "flight_type": "Bombing", "survivors": "Yes", "site": "Plain, Valley", "schedule": "Marham - Marham", "msn": null, "yom": null, "flight_number": null, "city": "Barton Bendish RLG", "zone": "Norfolk", "country": "United Kingdom", "region": "Europe", "crew_on_board": 6, "crew_fatalities": 0, "pax_on_board": 0, "pax_fatalities": 0, "other_fatalities": 0, "total_fatalities": 0, "captain_hours": null, "captain_hours_type": null, "copilot_hours": null, "copilot_hours_type": null, "aircraft_hours": null, "circumstances": "The airplane departed RAF Marham at 2110LT on September 7 on an operation to Berlin. It crash landed at 0430LT in a wheat field at Hall Farm, Barton Bendish, after flying from the Dutch coast with the starboard engine on fire. All six crew members survived. \r\nCrew:\r\nS/L H. L. Price, pilot, \r\nSgt Webber, \r\nF/S Woodmason, \r\nSgt Riley, \r\nSgt Giles, \r\nSgt Davidson.", "probable_cause": "Right engine on fire. "}