{"url": "https://www.baaa-acro.com/crash/crash-scan-30-pace-gannet-arno-atoll", "date": "Aug 1, 1972 at 0845 LT", "type": "SCAN-30", "operator": "Lagoon Aviation", "flight_phase": "Landing (descent or approach)", "flight_type": "Scheduled Revenue Flight", "survivors": "Yes", "site": "Lake, Sea, Ocean, River", "schedule": "Majuro - Arno Atoll", "msn": "34", "yom": 1949, "flight_number": null, "city": "Arno Atoll", "zone": "All Marshall Islands", "country": "Marshall Islands", "region": "Oceania", "crew_on_board": 1, "crew_fatalities": 0, "pax_on_board": 3, "pax_fatalities": 0, "other_fatalities": 0, "total_fatalities": 0, "captain_hours": 1698, "captain_hours_type": 21, "copilot_hours": null, "copilot_hours_type": null, "aircraft_hours": null, "circumstances": "Upon landing off the Arno Atoll on a short flight from Majuro, the amphibian airplane suffered a hull bow skin failure and sank. While all four occupants were rescued, the aircraft sank and its wreckage was not recovered. ", "probable_cause": "Due to lack of evidences, the exact cause of the accident could not be determined. "}