{"url": "https://www.baaa-acro.com/crash/crash-lisunov-li-2-ufa-7-killed", "date": "Nov 9, 1946", "type": "Lisunov LI-2", "operator": "Aeroflot-3", "flight_phase": "Landing (descent or approach)", "flight_type": "Scheduled Revenue Flight", "survivors": "No", "site": "Plain, Valley", "schedule": "Kuybyshev \u2013 Ufa \u2013 Sverdlovsk", "msn": "184 190 03", "yom": 21, "flight_number": "SU236", "city": "Ufa", "zone": "Republic of Bashkortostan", "country": "Russia", "region": "Asia", "crew_on_board": 4, "crew_fatalities": 4, "pax_on_board": 3, "pax_fatalities": 3, "other_fatalities": 0, "total_fatalities": 7, "captain_hours": null, "captain_hours_type": null, "copilot_hours": null, "copilot_hours_type": null, "aircraft_hours": 1470, "circumstances": "One hour and 35 minutes after its departure from Kuybyshev Airport, bound for Sverdlovsk, the oil pressure on the left engine dropped and the crew decided to shut it down and to feather the propeller. The captain decided to divert to Ufa for a safe landing but due to low clouds, he was unable to locate the airport. When the aircraft broke through the cloud layer, it was in fact above the city and when the crew increased power on the right engine, it failed because it overheat. In such conditions, the captain made a turn to leave the area and continued to the Belaya River to attempt an emergency landing. Eventually, the aircraft hit tree tops and crashed in flames in a wooded area near the river bank, killing all seven occupants.  ", "probable_cause": "Wrong decision on part of the crew who cut the wrong engine after failure."}