{"url": "https://www.baaa-acro.com/crash/ground-fire-beechcraft-99-brunswick", "date": "Mar 31, 1974 at 1710 LT", "type": "Beechcraft 99 Airliner", "operator": "Air%20South", "flight_phase": "Taxiing", "flight_type": "Scheduled Revenue Flight", "survivors": "Yes", "site": "Airport (less than 10 km from airport)", "schedule": "Brunswick - Atlanta", "msn": "U-077", "yom": 1969, "flight_number": null, "city": "Brunswick-Malcolm McKinnon", "zone": "Georgia", "country": "United States of America", "region": "North America", "crew_on_board": 2, "crew_fatalities": 0, "pax_on_board": 2, "pax_fatalities": 0, "other_fatalities": 0, "total_fatalities": 0, "captain_hours": 8900, "captain_hours_type": 130, "copilot_hours": null, "copilot_hours_type": null, "aircraft_hours": null, "circumstances": "While taxiing at Brunswick-Malcolm McKinnon Airport, a fie erupted on board and the crew immediately stopped the airplane. All four occupants escaped uninjured while the aircraft was destroyed by fire. ", "probable_cause": "The cause of fire could not be determined. However, heavy deposit of black soot was found in area adjacent to the power distribution panel."}