{"url": "https://www.baaa-acro.com/crash/crash-douglas-dc-3c-lubbock", "date": "Mar 11, 1971 at 1427 LT", "type": "Douglas DC-3", "operator": "FAA", "flight_phase": "Takeoff (climb)", "flight_type": "Calibration", "survivors": "Yes", "site": "Airport (less than 10 km from airport)", "schedule": "Lubbock - Lubbock", "msn": "10243", "yom": 1943, "flight_number": null, "city": "Lubbock", "zone": "Texas", "country": "United States of America", "region": "North America", "crew_on_board": 3, "crew_fatalities": 0, "pax_on_board": 0, "pax_fatalities": 0, "other_fatalities": 0, "total_fatalities": 0, "captain_hours": 7774, "captain_hours_type": 3364, "copilot_hours": null, "copilot_hours_type": null, "aircraft_hours": null, "circumstances": "The crew was engaged in a check of the Lubbock Airport facilities. During the takeoff roll, the airplane became uncontrollable, veered off runway and came to rest with its undercarriage raised. All three crew members were uninjured while the aircraft was damaged beyond repair. ", "probable_cause": "The crew failed to maintain directional control and failed to obtain/maintain flying speed. The following factors were reported: \r\n- Improper level off, \r\n- The aircraft veered with different engine power, \r\n- The tailwheel was not locked."}